{
  "status": "ok",
  "updated_at": "2026-05-22T06:37:54.426976Z",
  "source": "https://lotto.thaiorc.com/lao/last2/stats-years10.php",
  "period": "10 ปีย้อนหลัง",
  "data": {
    "description": "ดูผลการวิเคราะห์สถิติหวยลาว สถิติเลข 2 ตัว ที่ออกในย้อนหลัง 10 ปี วิเคราะห์ผลการออกสลากย้อนหลังอย่างละเอียด",
    "digit_position_stats": {
      "0": {
        "tens": 96,
        "units": 71,
        "total": 167
      },
      "1": {
        "tens": 101,
        "units": 74,
        "total": 175
      },
      "2": {
        "tens": 80,
        "units": 93,
        "total": 173
      },
      "3": {
        "tens": 94,
        "units": 85,
        "total": 179
      },
      "4": {
        "tens": 81,
        "units": 84,
        "total": 165
      },
      "5": {
        "tens": 90,
        "units": 86,
        "total": 176
      },
      "6": {
        "tens": 82,
        "units": 97,
        "total": 179
      },
      "7": {
        "tens": 101,
        "units": 91,
        "total": 192
      },
      "8": {
        "tens": 76,
        "units": 88,
        "total": 164
      },
      "9": {
        "tens": 87,
        "units": 119,
        "total": 206
      }
    },
    "frequency_distribution": {
      "15": [
        "24",
        "59"
      ],
      "14": [
        "09",
        "69",
        "99"
      ],
      "13": [
        "02",
        "03",
        "22",
        "38",
        "39",
        "68",
        "72",
        "77"
      ],
      "12": [
        "10",
        "16",
        "18",
        "26",
        "32",
        "36",
        "41",
        "53",
        "73",
        "79",
        "95"
      ],
      "11": [
        "11",
        "15",
        "74",
        "75",
        "87",
        "89",
        "96"
      ],
      "10": [
        "17",
        "19",
        "33",
        "45",
        "47",
        "49",
        "51",
        "56",
        "85"
      ],
      "9": [
        "05",
        "06",
        "34",
        "46",
        "57",
        "62",
        "64",
        "70",
        "97"
      ],
      "8": [
        "01",
        "07",
        "12",
        "13",
        "43",
        "48",
        "52",
        "54",
        "67",
        "76",
        "80",
        "86",
        "93",
        "98"
      ],
      "7": [
        "00",
        "04",
        "08",
        "14",
        "20",
        "28",
        "37",
        "78",
        "88",
        "92",
        "94"
      ],
      "6": [
        "27",
        "29",
        "30",
        "31",
        "35",
        "44",
        "50",
        "55",
        "58",
        "60",
        "61",
        "65",
        "66",
        "81",
        "90"
      ],
      "5": [
        "21",
        "25",
        "42",
        "63",
        "71",
        "82",
        "83",
        "84",
        "91"
      ],
      "4": [
        "23"
      ],
      "3": [
        "40"
      ]
    },
    "never_drawn": [],
    "never_drawn_count": 0
  }
}